skit_labels/__init__.py
skit_labels/cli.py
skit_labels/commands.py
skit_labels/constants.py
skit_labels/db.py
skit_labels/labelstudio/annotations.py
skit_labels/types.py
skit_labels/utils.py
skit_labels-0.3.37.dist-info/METADATA
skit_labels-0.3.37.dist-info/WHEEL
skit_labels-0.3.37.dist-info/entry_points.txt
skit_labels-0.3.37.dist-info/RECORD
